README.md
setup.py
dadosSPF/__init__.py
dadosSPF/dadosSPF.py
dadosSPF.egg-info/PKG-INFO
dadosSPF.egg-info/SOURCES.txt
dadosSPF.egg-info/dependency_links.txt
dadosSPF.egg-info/requires.txt
dadosSPF.egg-info/top_level.txt
dadosSPF.egg-info/.ipynb_checkpoints/PKG-INFO-checkpoint
dadosSPF.egg-info/.ipynb_checkpoints/SOURCES-checkpoint.txt
dadosSPF.egg-info/.ipynb_checkpoints/dependency_links-checkpoint.txt
dadosSPF.egg-info/.ipynb_checkpoints/requires-checkpoint.txt
dadosSPF.egg-info/.ipynb_checkpoints/top_level-checkpoint.txt