Metadata-Version: 2.1
Name: dadosSPF
Version: 1.1.8
Summary: Pacote de funções uteis para o desenvolvimento na cloudera
Home-page: https://gitlab.com.br/dadosSPF
Author: Carlos Piveta
Author-email: cepo496@gmail.com
License: MIT License
Keywords: Pacote
Platform: UNKNOWN
